AUTHORS.rst
CONTRIBUTING.rst
HISTORY.rst
LICENSE
MANIFEST.in
README.rst
pyproject.toml
setup.cfg
setup.py
docs/Makefile
docs/authors.rst
docs/bonndit.deconv.rst
docs/bonndit.rst
docs/bonndit.utils.rst
docs/conf.py
docs/contributing.rst
docs/history.rst
docs/index.rst
docs/installation.rst
docs/make.bat
docs/modules.rst
docs/readme.rst
docs/usage.rst
scripts/bundle-filtering
scripts/csd-peaks
scripts/data2fodf
scripts/dtiselectvols
scripts/kurtosis
scripts/low-rank-k-approx
scripts/mtdeconv
scripts/peak-modelling
scripts/prob-tracking
scripts/stdeconv
src/bonndit/__init__.py
src/bonndit/deconv/__init__.py
src/bonndit/deconv/base.py
src/bonndit/deconv/dki.py
src/bonndit/deconv/multivoxel.py
src/bonndit/deconv/shdeconv.py
src/bonndit/deconv/shoredeconv.py
src/bonndit/directions/__init__.pxd
src/bonndit/directions/__init__.py
src/bonndit/directions/__init__.pyx
src/bonndit/directions/csd_peaks.pyx
src/bonndit/directions/fodfapprox.pyx
src/bonndit/directions/watsonfit.py
src/bonndit/filter/__init__.py
src/bonndit/filter/filter.pyx
src/bonndit/pmodels/__init__.py
src/bonndit/pmodels/means.pxd
src/bonndit/pmodels/means.pyx
src/bonndit/pmodels/model_avg.pyx
src/bonndit/tracking/ItoW.pxd
src/bonndit/tracking/ItoW.pyx
src/bonndit/tracking/__init__.py
src/bonndit/tracking/alignedDirection.pxd
src/bonndit/tracking/alignedDirection.pyx
src/bonndit/tracking/alignedDirection_struct.pyx
src/bonndit/tracking/integration.pxd
src/bonndit/tracking/integration.pyx
src/bonndit/tracking/interpolation.pxd
src/bonndit/tracking/interpolation.pyx
src/bonndit/tracking/stopping.pxd
src/bonndit/tracking/stopping.pyx
src/bonndit/tracking/tracking_prob.pyx
src/bonndit/tracking/kalman/__init__.py
src/bonndit/tracking/kalman/kalman.pxd
src/bonndit/tracking/kalman/kalman.pyx
src/bonndit/tracking/kalman/model.pxd
src/bonndit/tracking/kalman/model.pyx
src/bonndit/utilc/__init__.pxd
src/bonndit/utilc/__init__.py
src/bonndit/utilc/average.pyx
src/bonndit/utilc/blas_lapack.pxd
src/bonnndit.egg-info/PKG-INFO
src/bonnndit.egg-info/SOURCES.txt
src/bonnndit.egg-info/dependency_links.txt
src/bonnndit.egg-info/not-zip-safe
src/bonnndit.egg-info/top_level.txt
