Metadata-Version: 2.1
Name: bonnndit
Version: 0.2.13
Summary: The bonndit package contains the latest diffusion imaging tools developed at the University of Bonn.
Home-page: https://github.com/MedVisBonn/bonndit
Author: Johannes Gruen
Author-email: jgruen@uni-bonn.de
License: GNU General Public License v3
Keywords: bonnndit
Platform: UNKNOWN
Classifier: Topic :: Scientific/Engineering
Classifier: Development Status :: 3 - Alpha
Classifier: Intended Audience :: Science/Research
Classifier: License :: OSI Approved :: GNU General Public License v3 (GPLv3)
Classifier: Natural Language :: English
Classifier: Programming Language :: Python :: 3.5
Classifier: Programming Language :: Python :: 3.6
Classifier: Programming Language :: Python :: 3.7
License-File: LICENSE
License-File: AUTHORS.rst
